simple_perms
